ktts/__init__.py
ktts_RedCatTeam-1.0.3.dist-info/LICENSE
ktts_RedCatTeam-1.0.3.dist-info/METADATA
ktts_RedCatTeam-1.0.3.dist-info/WHEEL
ktts_RedCatTeam-1.0.3.dist-info/top_level.txt
ktts_RedCatTeam-1.0.3.dist-info/RECORD
