Metadata-Version: 2.1
Name: ktts_RedCatTeam
Version: 1.0.3
Summary: A library for simple using RUTTS (Text to speech on russian language)
Author-email: RedCatTeam <evgeniy.coder@gmail.com>
Project-URL: Homepage, https://cat-ai-project.ru/ktts/
Project-URL: Issues, https://cat-ai-project.ru/ktts/issues
Classifier: Programming Language :: Python :: 3
Classifier: License :: OSI Approved :: MIT License
Classifier: Operating System :: OS Independent
Requires-Python: >=3.10
License-File: LICENSE
